chartsnap/__init__.py
chartsnap/main.py
chartsnap-0.1.dist-info/METADATA
chartsnap-0.1.dist-info/WHEEL
chartsnap-0.1.dist-info/entry_points.txt
chartsnap-0.1.dist-info/top_level.txt
chartsnap-0.1.dist-info/RECORD
